[
  {
    "sku_id": "SKU107",
    "item_description": "External Drive 1TB",
    "brand": "DataVault",
    "quantity": 4,
    "unit": "each",
    "size": "portable",
    "order_date": "2025-07-01",
    "order_timestamp": "2025-07-01 00:00:00",
    "country_code": "AU",
    "cost_centre_id": "CC_AU_005",
    "currency": "AUD",
    "unit_price": 24.4,
    "total_amount": 97.6,
    "order_id": "ORD_AU_452071",
    "line_number": 4,
    "requisitioner": "user_5668@company.com",
    "approval_status": "SUBMITTED",
    "delivery_date": "2025-07-10"
  },
  {
    "sku_id": "SKU110",
    "item_description": "Ethernet Cable - 10ft",
    "brand": "DataVault",
    "quantity": 6,
    "unit": "each",
    "size": "10ft",
    "order_date": "2025-07-01",
    "order_timestamp": "2025-07-01 00:00:00",
    "country_code": "AU",
    "cost_centre_id": "CC_AU_005",
    "currency": "AUD",
    "unit_price": 271.23,
    "total_amount": 1627.38,
    "order_id": "ORD_AU_303629",
    "line_number": 8,
    "requisitioner": "user_7856@company.com",
    "approval_status": "PENDING",
    "delivery_date": "2025-07-10"
  },
  {
    "sku_id": "SKU009",
    "item_description": "2m HDMI cable - ConnectPro",
    "brand": "ConnectPro",
    "quantity": 4,
    "unit": "each",
    "size": "2m",
    "order_date": "2025-07-03",
    "order_timestamp": "2025-07-03 00:00:00",
    "country_code": "AU",
    "cost_centre_id": "CC_AU_005",
    "currency": "AUD",
    "unit_price": 401.14,
    "total_amount": 1604.56,
    "order_id": "ORD_AU_619956",
    "line_number": 4,
    "requisitioner": "user_5714@company.com",
    "approval_status": "APPROVED",
    "delivery_date": "2025-07-09"
  },
  {
    "sku_id": "SKU102",
    "item_description": "LED Monitor 24 inch",
    "brand": "ViewMaster",
    "quantity": 2,
    "unit": "each",
    "size": "24 inch",
    "order_date": "2025-07-06",
    "order_timestamp": "2025-07-06 00:00:00",
    "country_code": "AU",
    "cost_centre_id": "CC_AU_005",
    "currency": "AUD",
    "unit_price": 418.81,
    "total_amount": 837.62,
    "order_id": "ORD_AU_707771",
    "line_number": 7,
    "requisitioner": "user_1451@company.com",
    "approval_status": "PENDING",
    "delivery_date": "2025-07-17"
  },
  {
    "sku_id": "SKU006",
    "item_description": "10ft HDMI Cable - ConnectPro",
    "brand": "ConnectPro",
    "quantity": 7,
    "unit": "each",
    "size": null,
    "order_date": "2025-07-09",
    "order_timestamp": "2025-07-09 00:00:00",
    "country_code": "AU",
    "cost_centre_id": "CC_AU_005",
    "currency": "AUD",
    "unit_price": 283.38,
    "total_amount": 1983.66,
    "order_id": "ORD_AU_934952",
    "line_number": 7,
    "requisitioner": "user_7496@company.com",
    "approval_status": "APPROVED",
    "delivery_date": "2025-07-16"
  },
  {
    "sku_id": null,
    "item_description": "Tax - sales tax",
    "brand": null,
    "quantity": 1,
    "unit": null,
    "size": null,
    "order_date": "2025-07-09",
    "order_timestamp": "2025-07-09 00:00:00",
    "country_code": "AU",
    "cost_centre_id": "CC_AU_005",
    "currency": "AUD",
    "unit_price": 24.95,
    "total_amount": 24.95,
    "order_id": "ORD_AU_852425",
    "line_number": 8,
    "requisitioner": "user_9127@company.com",
    "approval_status": "PENDING",
    "delivery_date": "2025-07-17"
  },
  {
    "sku_id": "SKU102",
    "item_description": "VIEWMASTER LED Monitor 24IN",
    "brand": "VIEWMASTER",
    "quantity": 1,
    "unit": "each",
    "size": "24in",
    "order_date": "2025-07-09",
    "order_timestamp": "2025-07-09 00:00:00",
    "country_code": "AU",
    "cost_centre_id": "CC_AU_005",
    "currency": "AUD",
    "unit_price": 258.1,
    "total_amount": 258.1,
    "order_id": "ORD_AU_812423",
    "line_number": 10,
    "requisitioner": "user_9979@company.com",
    "approval_status": "SUBMITTED",
    "delivery_date": "2025-07-21"
  },
  {
    "sku_id": "SKU102",
    "item_description": "ViewMaster LED Monitor 24&quot;",
    "brand": "ViewMaster",
    "quantity": 2,
    "unit": "each",
    "size": "24inch",
    "order_date": "2025-07-10",
    "order_timestamp": "2025-07-10 00:00:00",
    "country_code": "AU",
    "cost_centre_id": "CC_AU_005",
    "currency": "AUD",
    "unit_price": 392.61,
    "total_amount": 785.22,
    "order_id": "ORD_AU_178253",
    "line_number": 3,
    "requisitioner": "user_5411@company.com",
    "approval_status": "APPROVED",
    "delivery_date": "2025-07-17"
  },
  {
    "sku_id": "SKU113",
    "item_description": "ProConnect Wireless Earbuds White",
    "brand": "ProConnect",
    "quantity": 6,
    "unit": "pack",
    "size": "Compact",
    "order_date": "2025-07-10",
    "order_timestamp": "2025-07-10 00:00:00",
    "country_code": "AU",
    "cost_centre_id": "CC_AU_005",
    "currency": "AUD",
    "unit_price": 13.04,
    "total_amount": 78.24,
    "order_id": "ORD_AU_660571",
    "line_number": 6,
    "requisitioner": "user_6666@company.com",
    "approval_status": "SUBMITTED",
    "delivery_date": "2025-07-20"
  },
  {
    "sku_id": "SKU010",
    "item_description": "32 INCH MONITOR - ViewMaster",
    "brand": "viewmaster",
    "quantity": 5,
    "unit": "each",
    "size": "32 in",
    "order_date": "2025-07-13",
    "order_timestamp": "2025-07-13 00:00:00",
    "country_code": "AU",
    "cost_centre_id": "CC_AU_005",
    "currency": "AUD",
    "unit_price": 151.21,
    "total_amount": 756.05,
    "order_id": "ORD_AU_819737",
    "line_number": 2,
    "requisitioner": "user_2848@company.com",
    "approval_status": "APPROVED",
    "delivery_date": "2025-07-21"
  },
  {
    "sku_id": "SKU008",
    "item_description": "MECHANICAL KEYBOARD-COMPACT",
    "brand": "CONNECTPRO",
    "quantity": 7,
    "unit": "each",
    "size": "compact",
    "order_date": "2025-07-13",
    "order_timestamp": "2025-07-13 00:00:00",
    "country_code": "AU",
    "cost_centre_id": "CC_AU_005",
    "currency": "AUD",
    "unit_price": 118.83,
    "total_amount": 831.81,
    "order_id": "ORD_AU_812952",
    "line_number": 10,
    "requisitioner": "user_6807@company.com",
    "approval_status": "PENDING",
    "delivery_date": "2025-07-25"
  },
  {
    "sku_id": "SKU114",
    "item_description": "Portable SSD 512GB",
    "brand": "ConnectPro",
    "quantity": 5,
    "unit": "each",
    "size": "512GB",
    "order_date": "2025-07-19",
    "order_timestamp": "2025-07-19 00:00:00",
    "country_code": "AU",
    "cost_centre_id": "CC_AU_005",
    "currency": "AUD",
    "unit_price": 319.87,
    "total_amount": 1599.35,
    "order_id": "ORD_AU_254602",
    "line_number": 7,
    "requisitioner": "user_8934@company.com",
    "approval_status": "PENDING",
    "delivery_date": "2025-07-30"
  },
  {
    "sku_id": "SKU004",
    "item_description": "LCD27 inch monitr",
    "brand": "ViewMaster",
    "quantity": 2,
    "unit": "each",
    "size": "27 in",
    "order_date": "2025-07-19",
    "order_timestamp": "2025-07-19 00:00:00",
    "country_code": "AU",
    "cost_centre_id": "CC_AU_005",
    "currency": "AUD",
    "unit_price": 488.35,
    "total_amount": 976.7,
    "order_id": "ORD_AU_453976",
    "line_number": 5,
    "requisitioner": "user_3746@company.com",
    "approval_status": "APPROVED",
    "delivery_date": "2025-08-01"
  },
  {
    "sku_id": "SKU010",
    "item_description": "1TB External Hard Drive",
    "brand": "DataVault",
    "quantity": 1,
    "unit": "each",
    "size": null,
    "order_date": "2025-07-22",
    "order_timestamp": "2025-07-22 00:00:00",
    "country_code": "AU",
    "cost_centre_id": "CC_AU_005",
    "currency": "AUD",
    "unit_price": 80.84,
    "total_amount": 80.84,
    "order_id": "ORD_AU_536327",
    "line_number": 2,
    "requisitioner": "user_3636@company.com",
    "approval_status": "PENDING",
    "delivery_date": "2025-07-30"
  },
  {
    "sku_id": "SKU110",
    "item_description": "DataVault USB Drive 32GB",
    "brand": "DataVault",
    "quantity": 9,
    "unit": "each",
    "size": null,
    "order_date": "2025-07-24",
    "order_timestamp": "2025-07-24 00:00:00",
    "country_code": "AU",
    "cost_centre_id": "CC_AU_005",
    "currency": "AUD",
    "unit_price": 213.69,
    "total_amount": 1923.21,
    "order_id": "ORD_AU_863274",
    "line_number": 10,
    "requisitioner": "user_4163@company.com",
    "approval_status": "PENDING",
    "delivery_date": "2025-07-31"
  },
  {
    "sku_id": null,
    "item_description": "Warranty extension service",
    "brand": null,
    "quantity": 1,
    "unit": null,
    "size": null,
    "order_date": "2025-07-24",
    "order_timestamp": "2025-07-24 00:00:00",
    "country_code": "AU",
    "cost_centre_id": "CC_AU_005",
    "currency": "AUD",
    "unit_price": 180.6,
    "total_amount": 180.6,
    "order_id": "ORD_AU_458865",
    "line_number": 9,
    "requisitioner": "user_8007@company.com",
    "approval_status": "APPROVED",
    "delivery_date": "2025-07-31"
  },
  {
    "sku_id": "SKU009",
    "item_description": "Office Head Set Wired",
    "brand": "PC",
    "quantity": 3,
    "unit": "each",
    "size": "standard",
    "order_date": "2025-07-27",
    "order_timestamp": "2025-07-27 00:00:00",
    "country_code": "AU",
    "cost_centre_id": "CC_AU_005",
    "currency": "AUD",
    "unit_price": 419.94,
    "total_amount": 1259.82,
    "order_id": "ORD_AU_876504",
    "line_number": 8,
    "requisitioner": "user_5884@company.com",
    "approval_status": "APPROVED",
    "delivery_date": "2025-08-10"
  },
  {
    "sku_id": "SKU003",
    "item_description": "USB-C cable – 6ft",
    "brand": "ConnectPro",
    "quantity": 7,
    "unit": "each",
    "size": "6ft",
    "order_date": "2025-07-28",
    "order_timestamp": "2025-07-28 00:00:00",
    "country_code": "AU",
    "cost_centre_id": "CC_AU_005",
    "currency": "AUD",
    "unit_price": 455.82,
    "total_amount": 3190.74,
    "order_id": "ORD_AU_462004",
    "line_number": 2,
    "requisitioner": "user_1532@company.com",
    "approval_status": "PENDING",
    "delivery_date": "2025-08-06"
  },
  {
    "sku_id": "SKU008",
    "item_description": "viemaster 27 inch monitor",
    "brand": "VIEWMASTER",
    "quantity": 2,
    "unit": "each",
    "size": "27 inch",
    "order_date": "2025-07-30",
    "order_timestamp": "2025-07-30 00:00:00",
    "country_code": "AU",
    "cost_centre_id": "CC_AU_005",
    "currency": "AUD",
    "unit_price": 15.03,
    "total_amount": 30.06,
    "order_id": "ORD_AU_470570",
    "line_number": 2,
    "requisitioner": "user_2298@company.com",
    "approval_status": "APPROVED",
    "delivery_date": "2025-08-02"
  },
  {
    "sku_id": "SKU109",
    "item_description": "ETHERNET Cable 10 FT",
    "brand": "CONNECTPRO",
    "quantity": 6,
    "unit": "pack",
    "size": "10 ft",
    "order_date": "2025-07-31",
    "order_timestamp": "2025-07-31 00:00:00",
    "country_code": "AU",
    "cost_centre_id": "CC_AU_005",
    "currency": "AUD",
    "unit_price": 150.05,
    "total_amount": 900.3,
    "order_id": "ORD_AU_477195",
    "line_number": 1,
    "requisitioner": "user_8133@company.com",
    "approval_status": "APPROVED",
    "delivery_date": "2025-08-13"
  },
  {
    "sku_id": "SKU104",
    "item_description": "HD Webcam 1080p &lt;br&gt; DataVault",
    "brand": null,
    "quantity": 3,
    "unit": "each",
    "size": null,
    "order_date": "2025-08-01",
    "order_timestamp": "2025-08-01 00:00:00",
    "country_code": "AU",
    "cost_centre_id": "CC_AU_005",
    "currency": "AUD",
    "unit_price": 91.49,
    "total_amount": 274.47,
    "order_id": "ORD_AU_325832",
    "line_number": 6,
    "requisitioner": "user_1771@company.com",
    "approval_status": "PENDING",
    "delivery_date": "2025-08-08"
  },
  {
    "sku_id": "SKU002",
    "item_description": "Wired Mechanical Keyboard - blue switches",
    "brand": "Tech",
    "quantity": 3,
    "unit": "each",
    "size": "Full-size",
    "order_date": "2025-08-01",
    "order_timestamp": "2025-08-01 00:00:00",
    "country_code": "AU",
    "cost_centre_id": "CC_AU_005",
    "currency": "AUD",
    "unit_price": 345.65,
    "total_amount": 1036.95,
    "order_id": "ORD_AU_145665",
    "line_number": 10,
    "requisitioner": "user_9291@company.com",
    "approval_status": "SUBMITTED",
    "delivery_date": "2025-08-13"
  },
  {
    "sku_id": "SKU101",
    "item_description": "Wireless keyboard &amp; mouse set",
    "brand": "TechFlow",
    "quantity": 3,
    "unit": "each",
    "size": "Standard",
    "order_date": "2025-08-02",
    "order_timestamp": "2025-08-02 00:00:00",
    "country_code": "AU",
    "cost_centre_id": "CC_AU_005",
    "currency": "AUD",
    "unit_price": 305.99,
    "total_amount": 917.97,
    "order_id": "ORD_AU_262348",
    "line_number": 9,
    "requisitioner": "user_2625@company.com",
    "approval_status": "APPROVED",
    "delivery_date": "2025-08-16"
  },
  {
    "sku_id": "SKU010",
    "item_description": "32gb usb drv",
    "brand": "DV",
    "quantity": 2,
    "unit": "each",
    "size": "32 gigabytes",
    "order_date": "2025-08-02",
    "order_timestamp": "2025-08-02 00:00:00",
    "country_code": "AU",
    "cost_centre_id": "CC_AU_005",
    "currency": "AUD",
    "unit_price": 379.38,
    "total_amount": 758.76,
    "order_id": "ORD_AU_279931",
    "line_number": 4,
    "requisitioner": "user_4356@company.com",
    "approval_status": "PENDING",
    "delivery_date": "2025-08-09"
  },
  {
    "sku_id": "SKU120",
    "item_description": "VIEWmaster 22\" LCD monitor",
    "brand": "ViewMaster",
    "quantity": 6,
    "unit": "each",
    "size": "22 inch",
    "order_date": "2025-08-03",
    "order_timestamp": "2025-08-03 00:00:00",
    "country_code": "AU",
    "cost_centre_id": "CC_AU_005",
    "currency": "AUD",
    "unit_price": 467.47,
    "total_amount": 2804.82,
    "order_id": "ORD_AU_693715",
    "line_number": 5,
    "requisitioner": "user_9902@company.com",
    "approval_status": "SUBMITTED",
    "delivery_date": "2025-08-12"
  },
  {
    "sku_id": "SKU010",
    "item_description": "external ssd drive 512gb dvault",
    "brand": "dvault",
    "quantity": 3,
    "unit": "each",
    "size": null,
    "order_date": "2025-08-03",
    "order_timestamp": "2025-08-03 00:00:00",
    "country_code": "AU",
    "cost_centre_id": "CC_AU_005",
    "currency": "AUD",
    "unit_price": 210.22,
    "total_amount": 630.66,
    "order_id": "ORD_AU_820170",
    "line_number": 1,
    "requisitioner": "user_3474@company.com",
    "approval_status": "SUBMITTED",
    "delivery_date": "2025-08-14"
  },
  {
    "sku_id": "SKU111",
    "item_description": "DataVault 27\" 4K Monitor",
    "brand": "DataVault",
    "quantity": 1,
    "unit": "each",
    "size": "27 inch",
    "order_date": "2025-08-04",
    "order_timestamp": "2025-08-04 00:00:00",
    "country_code": "AU",
    "cost_centre_id": "CC_AU_005",
    "currency": "AUD",
    "unit_price": 106.69,
    "total_amount": 106.69,
    "order_id": "ORD_AU_722444",
    "line_number": 10,
    "requisitioner": "user_7479@company.com",
    "approval_status": "APPROVED",
    "delivery_date": "2025-08-07"
  },
  {
    "sku_id": null,
    "item_description": "Setup service installation",
    "brand": null,
    "quantity": 1,
    "unit": null,
    "size": null,
    "order_date": "2025-08-04",
    "order_timestamp": "2025-08-04 00:00:00",
    "country_code": "AU",
    "cost_centre_id": "CC_AU_005",
    "currency": "AUD",
    "unit_price": 341.72,
    "total_amount": 341.72,
    "order_id": "ORD_AU_455150",
    "line_number": 3,
    "requisitioner": "user_9847@company.com",
    "approval_status": "SUBMITTED",
    "delivery_date": "2025-08-07"
  },
  {
    "sku_id": "SKU008",
    "item_description": "64GB USB Drive",
    "brand": "TechFlow",
    "quantity": 14,
    "unit": "each",
    "size": "64GB",
    "order_date": "2025-08-04",
    "order_timestamp": "2025-08-04 00:00:00",
    "country_code": "AU",
    "cost_centre_id": "CC_AU_005",
    "currency": "AUD",
    "unit_price": 494.68,
    "total_amount": 6925.52,
    "order_id": "ORD_AU_283714",
    "line_number": 5,
    "requisitioner": "user_6916@company.com",
    "approval_status": "APPROVED",
    "delivery_date": "2025-08-18"
  },
  {
    "sku_id": null,
    "item_description": "Shipping fee express delivery",
    "brand": null,
    "quantity": 1,
    "unit": null,
    "size": null,
    "order_date": "2025-08-04",
    "order_timestamp": "2025-08-04 00:00:00",
    "country_code": "AU",
    "cost_centre_id": "CC_AU_005",
    "currency": "AUD",
    "unit_price": 81.98,
    "total_amount": 81.98,
    "order_id": "ORD_AU_269927",
    "line_number": 3,
    "requisitioner": "user_2937@company.com",
    "approval_status": "PENDING",
    "delivery_date": "2025-08-08"
  },
  {
    "sku_id": "SKU005",
    "item_description": "exteranl hard drive 1TB",
    "brand": "DataVault",
    "quantity": 1,
    "unit": "each",
    "size": "1TB",
    "order_date": "2025-08-07",
    "order_timestamp": "2025-08-07 00:00:00",
    "country_code": "AU",
    "cost_centre_id": "CC_AU_005",
    "currency": "AUD",
    "unit_price": 247.28,
    "total_amount": 247.28,
    "order_id": "ORD_AU_626346",
    "line_number": 2,
    "requisitioner": "user_3465@company.com",
    "approval_status": "PENDING",
    "delivery_date": "2025-08-16"
  },
  {
    "sku_id": "SKU118",
    "item_description": "Pro Connect Gaming Headset 5.1 Suround",
    "brand": "ProConnect",
    "quantity": 2,
    "unit": "each",
    "size": "Standard",
    "order_date": "2025-08-11",
    "order_timestamp": "2025-08-11 00:00:00",
    "country_code": "AU",
    "cost_centre_id": "CC_AU_005",
    "currency": "AUD",
    "unit_price": 385.93,
    "total_amount": 771.86,
    "order_id": "ORD_AU_762734",
    "line_number": 8,
    "requisitioner": "user_6451@company.com",
    "approval_status": "PENDING",
    "delivery_date": "2025-08-19"
  },
  {
    "sku_id": "SKU108",
    "item_description": "Ethernet Cable 10 ft pack",
    "brand": "ConnectPro",
    "quantity": 3,
    "unit": "pack",
    "size": "10ft",
    "order_date": "2025-08-12",
    "order_timestamp": "2025-08-12 00:00:00",
    "country_code": "AU",
    "cost_centre_id": "CC_AU_005",
    "currency": "AUD",
    "unit_price": 427.94,
    "total_amount": 1283.82,
    "order_id": "ORD_AU_882598",
    "line_number": 5,
    "requisitioner": "user_5353@company.com",
    "approval_status": "APPROVED",
    "delivery_date": "2025-08-15"
  },
  {
    "sku_id": "SKU109",
    "item_description": "Gaming Headset &lt;/b&gt; ConnectPro",
    "brand": null,
    "quantity": 1,
    "unit": null,
    "size": "Red On-ear",
    "order_date": "2025-08-13",
    "order_timestamp": "2025-08-13 00:00:00",
    "country_code": "AU",
    "cost_centre_id": "CC_AU_005",
    "currency": "AUD",
    "unit_price": 175.31,
    "total_amount": 175.31,
    "order_id": "ORD_AU_561892",
    "line_number": 4,
    "requisitioner": "user_1207@company.com",
    "approval_status": "SUBMITTED",
    "delivery_date": "2025-08-22"
  },
  {
    "sku_id": "SKU106",
    "item_description": "USB-C to HDMI Adptr &#x2013; ConnectPro",
    "brand": "ConnectPro",
    "quantity": 1,
    "unit": null,
    "size": null,
    "order_date": "2025-08-13",
    "order_timestamp": "2025-08-13 00:00:00",
    "country_code": "AU",
    "cost_centre_id": "CC_AU_005",
    "currency": "AUD",
    "unit_price": 343.78,
    "total_amount": 343.78,
    "order_id": "ORD_AU_543094",
    "line_number": 1,
    "requisitioner": "user_2194@company.com",
    "approval_status": "APPROVED",
    "delivery_date": "2025-08-18"
  },
  {
    "sku_id": null,
    "item_description": "Setup service charge",
    "brand": null,
    "quantity": 1,
    "unit": "service",
    "size": null,
    "order_date": "2025-08-13",
    "order_timestamp": "2025-08-13 00:00:00",
    "country_code": "AU",
    "cost_centre_id": "CC_AU_005",
    "currency": "AUD",
    "unit_price": 60.16,
    "total_amount": 60.16,
    "order_id": "ORD_AU_434181",
    "line_number": 1,
    "requisitioner": "user_6383@company.com",
    "approval_status": "SUBMITTED",
    "delivery_date": "2025-08-23"
  },
  {
    "sku_id": "SKU103",
    "item_description": "Usb-C 6feet cabl",
    "brand": "DataVault",
    "quantity": 1,
    "unit": "pack",
    "size": "6ft",
    "order_date": "2025-08-17",
    "order_timestamp": "2025-08-17 00:00:00",
    "country_code": "AU",
    "cost_centre_id": "CC_AU_005",
    "currency": "AUD",
    "unit_price": 132.57,
    "total_amount": 132.57,
    "order_id": "ORD_AU_501406",
    "line_number": 7,
    "requisitioner": "user_4388@company.com",
    "approval_status": "APPROVED",
    "delivery_date": "2025-08-26"
  },
  {
    "sku_id": "SKU003",
    "item_description": "ConnectPro USB-C Cable &#x2013; 1m",
    "brand": "CONNECTPRO",
    "quantity": 4,
    "unit": "each",
    "size": "1m",
    "order_date": "2025-08-19",
    "order_timestamp": "2025-08-19 00:00:00",
    "country_code": "AU",
    "cost_centre_id": "CC_AU_005",
    "currency": "AUD",
    "unit_price": 412.55,
    "total_amount": 1650.2,
    "order_id": "ORD_AU_898998",
    "line_number": 2,
    "requisitioner": "user_3678@company.com",
    "approval_status": "SUBMITTED",
    "delivery_date": "2025-08-28"
  },
  {
    "sku_id": null,
    "item_description": "Tax - sales tax",
    "brand": null,
    "quantity": 1,
    "unit": null,
    "size": null,
    "order_date": "2025-08-20",
    "order_timestamp": "2025-08-20 00:00:00",
    "country_code": "AU",
    "cost_centre_id": "CC_AU_005",
    "currency": "AUD",
    "unit_price": 340.26,
    "total_amount": 340.26,
    "order_id": "ORD_AU_522133",
    "line_number": 4,
    "requisitioner": "user_8779@company.com",
    "approval_status": "APPROVED",
    "delivery_date": "2025-09-03"
  },
  {
    "sku_id": "SKU008",
    "item_description": "mech keybrd",
    "brand": null,
    "quantity": 3,
    "unit": "each",
    "size": "compact",
    "order_date": "2025-08-22",
    "order_timestamp": "2025-08-22 00:00:00",
    "country_code": "AU",
    "cost_centre_id": "CC_AU_005",
    "currency": "AUD",
    "unit_price": 220.83,
    "total_amount": 662.49,
    "order_id": "ORD_AU_565188",
    "line_number": 7,
    "requisitioner": "user_2841@company.com",
    "approval_status": "PENDING",
    "delivery_date": "2025-08-29"
  },
  {
    "sku_id": "SKU005",
    "item_description": "External Hard Drive - 1TB",
    "brand": "DataVault",
    "quantity": 2,
    "unit": "each",
    "size": "1TB",
    "order_date": "2025-08-25",
    "order_timestamp": "2025-08-25 00:00:00",
    "country_code": "AU",
    "cost_centre_id": "CC_AU_005",
    "currency": "AUD",
    "unit_price": 184.42,
    "total_amount": 368.84,
    "order_id": "ORD_AU_387197",
    "line_number": 1,
    "requisitioner": "user_9721@company.com",
    "approval_status": "APPROVED",
    "delivery_date": "2025-09-06"
  },
  {
    "sku_id": "SKU116",
    "item_description": "DataVault HDMI 15 ft cable",
    "brand": "DataVault",
    "quantity": 8,
    "unit": "each",
    "size": "15 ft",
    "order_date": "2025-08-27",
    "order_timestamp": "2025-08-27 00:00:00",
    "country_code": "AU",
    "cost_centre_id": "CC_AU_005",
    "currency": "AUD",
    "unit_price": 221.13,
    "total_amount": 1769.04,
    "order_id": "ORD_AU_215393",
    "line_number": 10,
    "requisitioner": "user_9120@company.com",
    "approval_status": "SUBMITTED",
    "delivery_date": "2025-09-05"
  },
  {
    "sku_id": "SKU009",
    "item_description": "HDMI Cable 10ft pack ConnectPro",
    "brand": "ConnectPro",
    "quantity": 1,
    "unit": "pack",
    "size": "10ft",
    "order_date": "2025-08-27",
    "order_timestamp": "2025-08-27 00:00:00",
    "country_code": "AU",
    "cost_centre_id": "CC_AU_005",
    "currency": "AUD",
    "unit_price": 127.35,
    "total_amount": 127.35,
    "order_id": "ORD_AU_482239",
    "line_number": 9,
    "requisitioner": "user_5002@company.com",
    "approval_status": "APPROVED",
    "delivery_date": "2025-09-02"
  },
  {
    "sku_id": "SKU107",
    "item_description": "techflow mehanical keyboard rgb",
    "brand": "techflow",
    "quantity": 1,
    "unit": "each",
    "size": "Full-size",
    "order_date": "2025-08-29",
    "order_timestamp": "2025-08-29 00:00:00",
    "country_code": "AU",
    "cost_centre_id": "CC_AU_005",
    "currency": "AUD",
    "unit_price": 16.96,
    "total_amount": 16.96,
    "order_id": "ORD_AU_889149",
    "line_number": 10,
    "requisitioner": "user_1097@company.com",
    "approval_status": "SUBMITTED",
    "delivery_date": "2025-09-04"
  },
  {
    "sku_id": null,
    "item_description": "Express delivery service charge",
    "brand": null,
    "quantity": 1,
    "unit": "service",
    "size": null,
    "order_date": "2025-08-29",
    "order_timestamp": "2025-08-29 00:00:00",
    "country_code": "AU",
    "cost_centre_id": "CC_AU_005",
    "currency": "AUD",
    "unit_price": 428.23,
    "total_amount": 428.23,
    "order_id": "ORD_AU_653931",
    "line_number": 2,
    "requisitioner": "user_2467@company.com",
    "approval_status": "APPROVED",
    "delivery_date": "2025-09-09"
  }
]